cleanX/__init__.py
cleanX/__main__.py
cleanX/cli/__init__.py
cleanX/cli/dataset.py
cleanX/cli/dicom.py
cleanX/cli/images.py
cleanX/cli/main.py
cleanX/dataset_processing/__init__.py
cleanX/dataset_processing/dataframes.py
cleanX/dicom_processing/__init__.py
cleanX/dicom_processing/pydicom_adapter.py
cleanX/dicom_processing/simpleitk_adapter.py
cleanX/dicom_processing/source.py
cleanX/image_work/__init__.py
cleanX/image_work/image_functions.py
cleanX/image_work/journaling_pipeline.py
cleanX/image_work/pipeline.py
cleanX/image_work/steps.py
cleanX-0.1.13.dist-info/LICENSE
cleanX-0.1.13.dist-info/METADATA
cleanX-0.1.13.dist-info/WHEEL
cleanX-0.1.13.dist-info/top_level.txt
cleanX-0.1.13.dist-info/RECORD
