Metadata-Version: 2.1
Name: cleanX
Version: 0.1.13
Summary: Python library for cleaning data in large datasets of Xrays
Home-page: https://github.com/drcandacemakedamoore/cleanX
Author: doctormakeda@gmail.com
Author-email: doctormakeda@gmail.com
Maintainer: doctormakeda@gmail.com
Maintainer-email: doctormakeda@gmail.com
License: MIT
Platform: UNKNOWN
Requires-Dist: pandas
Requires-Dist: numpy
Requires-Dist: matplotlib
Requires-Dist: pillow
Requires-Dist: tesserocr
Requires-Dist: opencv-python
Requires-Dist: pytz
Provides-Extra: cli
Requires-Dist: click ; extra == 'cli'
Provides-Extra: dev
Requires-Dist: wheel ; extra == 'dev'
Requires-Dist: sphinx ; extra == 'dev'
Requires-Dist: pytest ; extra == 'dev'
Requires-Dist: codestyle ; extra == 'dev'
Requires-Dist: click ; extra == 'dev'
Requires-Dist: pydicom ; extra == 'dev'
Requires-Dist: SimpleITK ; extra == 'dev'
Provides-Extra: pydicom
Requires-Dist: pydicom ; extra == 'pydicom'
Provides-Extra: simpleitk
Requires-Dist: SimpleITK ; extra == 'simpleitk'
